Light_Qiwi/Callback.py
Light_Qiwi/Enums.py
Light_Qiwi/Errors.py
Light_Qiwi/Objects.py
Light_Qiwi/Qiwi.py
Light_Qiwi/Utils.py
Light_Qiwi/__init__.py
Light_Qiwi-1.1.1.dist-info/METADATA
Light_Qiwi-1.1.1.dist-info/WHEEL
Light_Qiwi-1.1.1.dist-info/top_level.txt
Light_Qiwi-1.1.1.dist-info/RECORD
