Metadata-Version: 2.1
Name: Light-Qiwi
Version: 1.1.1
Summary: Python модуль для написания скриптов для Qiwi (qiwi.com) (API wrapper)
Home-page: https://github.com/vffuunnyy/Light_Qiwi
Author: vffuunnyy
Author-email: vffuunnyy@gmail.com
License: Apache License, Version 2.0
Platform: UNKNOWN
Classifier: Programming Language :: Python :: 3.5
Classifier: Programming Language :: Python :: 3.6
Classifier: Programming Language :: Python :: 3.7
Classifier: Programming Language :: Python :: Implementation :: PyPy
Classifier: License :: OSI Approved :: MIT License
Classifier: Operating System :: OS Independent
Requires-Dist: requests
Requires-Dist: cherrypy
Requires-Dist: aenum
